{
  "theClanless:Acrobatics": {
    "NAME": "Acrobatics",
    "DESCRIPTION": "Gain !M! Buffer.",
    "UPGRADE_DESCRIPTION": "Gain !M! Buffer. NL Your next attack costs 1 less Energy."
  },
  "theClanless:Blur": {
    "NAME": "Blur",
    "DESCRIPTION": "Deal !D! damage !M! times."
  },
  "theClanless:BoxedIn": {
    "NAME": "Boxed In",
    "DESCRIPTION": "Gain !M! theclanless:Press. NL Exhaust.",
    "UPGRADE_DESCRIPTION": "Gain !M! theclanless:Press."
  },
  "theClanless:CatBurglary": {
    "NAME": "Cat Burglary",
    "DESCRIPTION": "Deal !D! damage and gain !D! X !M! gold. Exhaust.",
    "UPGRADE_DESCRIPTION": "Deal !D! damage and gain !D! X !M! gold. Exhaust."
  },
  "theClanless:ComputerHacking": {
    "NAME": "Computer Hacking",
    "DESCRIPTION": "Deal !D! damage and apply !M! Vulnerable.",
    "UPGRADE_DESCRIPTION": "Deal !D! damage and apply !M! Vulnerable."
  },
  "theClanless:Distraction": {
    "NAME": "Distraction",
    "DESCRIPTION": "Draw !M! cards. Discard 2.",
    "UPGRADE_DESCRIPTION": "Draw !M! cards. Discard 2."
  },
  "theClanless:Dodge": {
    "NAME": "Dodge",
    "DESCRIPTION": "Gain !B! Block.",
    "UPGRADE_DESCRIPTION": "Gain !B! Block. "
  },
  "theClanless:FakeOut": {
    "NAME": "Fake Out",
    "DESCRIPTION": "Gain !M! theclanless:Maneuver. NL Exhaust.",
    "UPGRADE_DESCRIPTION": "Gain !M! theclanless:Maneuver."
  },
  "theClanless:FastHands": {
    "NAME": "Fast Hands",
    "DESCRIPTION": "Retrieve a card from your discard pile and reduce it's cost by !M! . NL The retrieved card Exhausts.",
    "UPGRADE_DESCRIPTION": "Retrieve a card from your discard pile and reduce it's cost by !M! . NL The retrieved card Exhausts."
  },
  "theClanless:FistsOfDeath": {
    "NAME": "Fists of Death",
    "DESCRIPTION": "Gain !M! Strength.",
    "UPGRADE_DESCRIPTION": "Gain !M! Strength."
  },
  "theClanless:Flash": {
    "NAME": "Flash",
    "DESCRIPTION": "Gain !M! theclanless:maneuvers and draw a card.",
    "UPGRADE_DESCRIPTION": "Gain !M! theclanless:maneuvers and draw a card."
  },
  "theClanless:GrowingFury": {
    "NAME": "Growing Fury",
    "DESCRIPTION": "Deal !D! damage. Consume a theclanless:press to increase the damage of this card by !M!",
    "UPGRADE_DESCRIPTION": "Deal !D! damage. Consume a theclanless:press to increase the damage of this card by !M!"
  },
  "theClanless:IncreasedStrength": {
    "NAME": "Increased Strength",
    "DESCRIPTION": "Increase the damage of all Potence attacks by !M! for the remainder of combat.",
    "UPGRADE_DESCRIPTION": "Increase the damage of all Potence attacks by !M! for the remainder of combat."
  },
  "theClanless:InfernalPursuit": {
    "NAME": "Infernal Pursuit",
    "DESCRIPTION": "Whenever you play a card, draw a card.",
    "UPGRADE_DESCRIPTION": "Whenever you play a card, draw !M! cards."
  },
  "theClanless:ImmortalGrapple": {
    "NAME": "Immortal Grapple",
    "DESCRIPTION": "Deal !D! damage. Consume theclanless:presses to apply Constricted equal to !M! + consumed presses. Otherwise, gain !M! presses.",
    "UPGRADE_DESCRIPTION": "Deal !D! damage. Consume theclanless:presses to apply Constricted equal to !M! + consumed presses. Otherwise, gain !M! presses."
  },
  "theClanless:LuckyBlow": {
    "NAME": "Lucky Blow",
    "DESCRIPTION": "Deal !D! damage.",
    "UPGRADE_DESCRIPTION": "Deal !D! damage. NL Exhaust. "
  },
  "theClanless:MightyGrapple": {
    "NAME": "Mighty Grapple",
    "DESCRIPTION": "Deal !D! damage and gain !M! theclanless:press.",
    "UPGRADE_DESCRIPTION": "Deal !D! damage and gain !M! theclanless:press."
  },
  "theClanless:NimbleFeet": {
    "NAME": "Nimble Feet",
    "DESCRIPTION": "Your next Skill is played twice.",
    "UPGRADE_DESCRIPTION": "Your next skill and next attack are played twice."
  },
  "theClanless:Psyche": {
    "NAME": "Psyche!",
    "DESCRIPTION": "Gain !M! theclanless:Maneuvers.",
    "UPGRADE_DESCRIPTION":  "Gain !M! theclanless:Maneuvers. NL Take another turn after this one, keeping all theclanless:maneuvers. NL Exhaust."
  },
  "theClanless:PulledFangs": {
    "NAME": "Pulled Fangs",
    "DESCRIPTION": "Deal !D! damage and apply !M! weakness. If your last card played was an attack gain 1 energy.",
    "UPGRADE_DESCRIPTION":  "Deal !D! damage and apply !M! weakness. If your last card played was an attack gain 1 energy."
  },
  "theClanless:RapidHealing": {
    "NAME": "Rapid Healing",
    "DESCRIPTION": "Lose all regeneration. Gain !M! regeneration X times. NL Exhaust.",
    "UPGRADE_DESCRIPTION":  "Lose all regeneration. Gain !M! regeneration X+1 times. NL Exhaust."
  },
  "theClanless:Sideslip": {
    "NAME": "Sideslip",
    "DESCRIPTION": "Gain !M! theclanless:Maneuvers each turn.",
    "UPGRADE_DESCRIPTION":  "Gain !M! theclanless:Maneuvers each turn."
  },
  "theClanless:SkinOfRock": {
    "NAME": "Skin of Rock",
    "DESCRIPTION": "Gain !B! block.",
    "UPGRADE_DESCRIPTION":  "Gain !B! block twice."
  },
  "theClanless:TasteOfVitae": {
    "NAME": "Taste of Vitae",
    "DESCRIPTION": "Gain !M! theclanless:Bloodheal. NL Exhaust.",
    "UPGRADE_DESCRIPTION": "Gain !M! theclanless:Bloodheal. NL Exhaust."
  },
  "theClanless:TornSignpost": {
    "NAME": "Torn Signpost",
    "DESCRIPTION": "Gain !M! strength. Lose !M! strength at the end of your turn. NL Innate.",
    "UPGRADE_DESCRIPTION": "Gain !M! strength this turn. Keep 2 strength, lose the rest at the end of your turn. NL Innate. Exhaust."
  },
  "theClanless:ItsaTrap": {
    "NAME": "Trap!",
    "DESCRIPTION": "Whenever you gain a theclanless:press, gain another press.",
    "UPGRADE_DESCRIPTION": "Whenever you gain a theclanless:press, gain another press."
  },
  "theClanless:UndeadStrength": {
    "NAME": "Undead Strength",
    "DESCRIPTION": "Deal !D! damage.",
    "UPGRADE_DESCRIPTION": "Deal !D! damage."
  },
  "theClanless:UnflinchingPersistence": {
    "NAME": "Unflinching Persistence",
    "DESCRIPTION": "Gain !B! block. Increase the block of all Unflinching Persistence by !M!.",
    "UPGRADE_DESCRIPTION": "Gain !B! block. Increase the block of all Unflinching Persistence by !M!."
  },
  "theClanless:VampiricSpeed": {
    "NAME": "Vampiric Speed",
    "DESCRIPTION": "Gain !B! block. Consume 1 theclanless:maneuver to gain !M! block.",
    "UPGRADE_DESCRIPTION": "Gain !B! block. Consume up to 2 theclanless:maneuvers to gain !M! block each."
  },
  "theClanless:WakeWithEveningsFreshness": {
    "NAME": "Wake w/ Evening Freshness",
    "DESCRIPTION": "Gain !B! block. If target monster intends to attack gain !M! dexterity.",
    "UPGRADE_DESCRIPTION": "Gain !B! block. If target monster intends to attack gain !M! dexterity"
  },
  "theClanless:DefaultCommonAttack": {
    "NAME": "Strike",
    "DESCRIPTION": "Deal !D! damage. NL [#0000ff]This[] [#ff0000]Is[] [#ffff00]How[] [#88888]color[] [#ff00ff]works.[]"
  },
  "theClanless:DefaultCommonSkill": {
    "NAME": "Defend",
    "DESCRIPTION": "Gain !B! Block. NL theclanless:Multiword_Keyword."
  },
  "theClanless:DefaultCommonPower": {
    "NAME": "Hold Place",
    "DESCRIPTION": "Gain !M! theclanless:Keyword.",
    "UPGRADE_DESCRIPTION": "Gain !M! theclanless:Keywords."
  },
  "theClanless:DefaultUncommonAttack": {
    "NAME": "Big slap",
    "DESCRIPTION": "Deal !D! damage."
  },
  "theClanless:DefaultUncommonSkill": {
    "NAME": "A Better Defend",
    "DESCRIPTION": "Gain !B! Plated Armor. Affected by Dexterity."
  },
  "theClanless:DefaultUncommonPower": {
    "NAME": "Weirdness",
    "DESCRIPTION": "Gain X theclanless:Keywords.",
    "UPGRADE_DESCRIPTION": "Gain X +1 theclanless:Keywords."
  },
  "theClanless:DefaultRareAttack": {
    "NAME": "TOUCH",
    "DESCRIPTION": "Deal !D! damage."
  },
  "theClanless:DefaultRareSkill": {
    "NAME": "For Each Loop x2",
    "DESCRIPTION": "Apply !M! Vulnerable to all enemies, 2 times.",
    "UPGRADE_DESCRIPTION": "Apply !M! Vulnerable to all enemies, 3 times."
  },
  "theClanless:DefaultRarePower": {
    "NAME": "In-Progress Form",
    "DESCRIPTION": "At the start of your turn, play a TOUCH."
  },
  "theClanless:DefaultAttackWithVariable": {
    "NAME": "Special Strike",
    "DESCRIPTION": "Deal !D! damage [E] times. NL (Deal !theclanless:ENERGY_DAMAGE! damage total.)"
  },
  "theClanless:DefaultSecondMagicNumberSkill": {
    "NAME": "Cool 2 Number Card",
    "DESCRIPTION": "Apply !M! Vulnerable and !theclanless:SM! poison to an enemy."
  },
  "theClanless:OrbSkill": {
    "NAME": "Get Orb",
    "DESCRIPTION": "Channel 1 Default Orb."
  }
}
